topsis/__init__.py
topsis/topsis.py
Topsis_Lovepreet_101903732-0.0.3.dist-info/LICENSE
Topsis_Lovepreet_101903732-0.0.3.dist-info/METADATA
Topsis_Lovepreet_101903732-0.0.3.dist-info/WHEEL
Topsis_Lovepreet_101903732-0.0.3.dist-info/top_level.txt
Topsis_Lovepreet_101903732-0.0.3.dist-info/RECORD
