Metadata-Version: 2.1
Name: Topsis-Lovepreet-101903732
Version: 0.0.3
Summary: Implement TOPSIS on a dataset through command line
Home-page: UNKNOWN
Author: Lovepreet Singh
Author-email: lovithindcoc@gmail.com
License: UNKNOWN
Keywords: python,topsis
Platform: UNKNOWN
Classifier: Development Status :: 1 - Planning
Classifier: Intended Audience :: Developers
Classifier: Programming Language :: Python :: 3
Classifier: Operating System :: Unix
Classifier: Operating System :: MacOS :: MacOS X
Classifier: Operating System :: Microsoft :: Windows
License-File: LICENSE
Requires-Dist: pandas
Requires-Dist: numpy
